OpencvJishiRumenChuyiFix1/README.md
OpencvJishiRumenChuyiFix1/__init__.py
OpencvJishiRumenChuyiFix1/__main__.py
OpencvJishiRumenChuyiFix1/file.epub
OpencvJishiRumenChuyiFix1/index.html
OpencvJishiRumenChuyiFix1/css/__init__.py
OpencvJishiRumenChuyiFix1/css/annotations.css
OpencvJishiRumenChuyiFix1/css/main.css
OpencvJishiRumenChuyiFix1/css/normalize.css
OpencvJishiRumenChuyiFix1/css/popup.css
OpencvJishiRumenChuyiFix1/font/__init__.py
OpencvJishiRumenChuyiFix1/font/fontello.eot
OpencvJishiRumenChuyiFix1/font/fontello.svg
OpencvJishiRumenChuyiFix1/font/fontello.ttf
OpencvJishiRumenChuyiFix1/font/fontello.woff
OpencvJishiRumenChuyiFix1/img/__init__.py
OpencvJishiRumenChuyiFix1/img/annotator-glyph-sprite.png
OpencvJishiRumenChuyiFix1/img/annotator-icon-sprite.png
OpencvJishiRumenChuyiFix1/img/apple-touch-icon.png
OpencvJishiRumenChuyiFix1/img/cancelfullscreen.png
OpencvJishiRumenChuyiFix1/img/close.png
OpencvJishiRumenChuyiFix1/img/fullscreen.png
OpencvJishiRumenChuyiFix1/img/loader.gif
OpencvJishiRumenChuyiFix1/img/menu-icon.png
OpencvJishiRumenChuyiFix1/img/save.png
OpencvJishiRumenChuyiFix1/img/saved.png
OpencvJishiRumenChuyiFix1/img/settings-s.png
OpencvJishiRumenChuyiFix1/img/settings.png
OpencvJishiRumenChuyiFix1/img/star.png
OpencvJishiRumenChuyiFix1/js/__init__.py
OpencvJishiRumenChuyiFix1/js/epub.js
OpencvJishiRumenChuyiFix1/js/epub.min.js
OpencvJishiRumenChuyiFix1/js/epub.min.map
OpencvJishiRumenChuyiFix1/js/hooks.min.js
OpencvJishiRumenChuyiFix1/js/hooks.min.map
OpencvJishiRumenChuyiFix1/js/reader.js
OpencvJishiRumenChuyiFix1/js/reader.js.map
OpencvJishiRumenChuyiFix1/js/reader.min.js
OpencvJishiRumenChuyiFix1/js/reader.min.map
OpencvJishiRumenChuyiFix1/js/hooks/__init__.py
OpencvJishiRumenChuyiFix1/js/hooks/extensions/__init__.py
OpencvJishiRumenChuyiFix1/js/hooks/extensions/highlight.js
OpencvJishiRumenChuyiFix1/js/libs/__init__.py
OpencvJishiRumenChuyiFix1/js/libs/jquery.min.js
OpencvJishiRumenChuyiFix1/js/libs/localforage.min.js
opencv_jishi_rumen_chuyi_fix1-2025.3.25.0.dist-info/METADATA
opencv_jishi_rumen_chuyi_fix1-2025.3.25.0.dist-info/WHEEL
opencv_jishi_rumen_chuyi_fix1-2025.3.25.0.dist-info/entry_points.txt
opencv_jishi_rumen_chuyi_fix1-2025.3.25.0.dist-info/top_level.txt
opencv_jishi_rumen_chuyi_fix1-2025.3.25.0.dist-info/RECORD
